{
  "project_info": {
    "project_number": "87887858072",
    "project_id": "computerengineeringdesign2",
    "storage_bucket": "computerengineeringdesign2.appspot.com"
  },
  "client": [
    {
      "client_info": {
        "mobilesdk_app_id": "1:87887858072:android:5eb3bc51b601510fef43ed",
        "android_client_info": {
          "package_name": "com.example.computerengineeringdesign2"
        }
      },
      "oauth_client": [
        {
          "client_id": "87887858072-17qfi0o9u714t9mcib1mnqskoas2vodl.apps.googleusercontent.com",
          "client_type": 3
        }
      ],
      "api_key": [
        {
          "current_key": "AIzaSyBfl52EOblENnUuARHJMTorcQnii-HAcj4"
        }
      ],
      "services": {
        "appinvite_service": {
          "other_platform_oauth_client": [
            {
              "client_id": "87887858072-17qfi0o9u714t9mcib1mnqskoas2vodl.apps.googleusercontent.com",
              "client_type": 3
            }
          ]
        }
      }
    }
  ],
  "configuration_version": "1"
}